LICENSE
MANIFEST.in
README.rst
runtests.py
setup.py
rest_condition/__init__.py
rest_condition/permissions.py
rest_condition.egg-info/PKG-INFO
rest_condition.egg-info/SOURCES.txt
rest_condition.egg-info/dependency_links.txt
rest_condition.egg-info/requires.txt
rest_condition.egg-info/top_level.txt