Metadata-Version: 1.1
Name: rest-condition
Version: 1.0.3
Summary: Complex permissions flow for django-rest-framework
Home-page: https://github.com/caxap/rest_condition
Author: Maxim Kamenkov
Author-email: mkamenkov@gmail.com
License: MIT
Platform: UNKNOWN
Classifier: Development Status :: 5 - Production/Stable
Classifier: Framework :: Django
Classifier: Intended Audience :: Developers
Classifier: Natural Language :: English
Classifier: License :: OSI Approved :: MIT License
Classifier: Programming Language :: Python
Classifier: Programming Language :: Python :: 2.6
Classifier: Programming Language :: Python :: 2.7
Classifier: Programming Language :: Python :: 3
Classifier: Programming Language :: Python :: 3.3
Classifier: Programming Language :: Python :: 3.4
